{
"checked_at": "2026-07-18T05:01:53Z",
"cameras": 1523,
"counts": {
"offline": 17,
"placeholder": 41,
"frozen": 2
},
"status": {
"https://images.wsdot.wa.gov/SC/182vc00238.jpg": "offline",
"https://images.wsdot.wa.gov/nc/002vc14457.jpg": "placeholder",
"https://images.wsdot.wa.gov/nc/017vc05656.jpg": "placeholder",
"https://images.wsdot.wa.gov/nc/028vc02490.jpg": "placeholder",
"https://images.wsdot.wa.gov/nc/028vc05286.jpg": "placeholder",
"https://images.wsdot.wa.gov/nc/097vc29902.jpg": "placeholder",
"https://images.wsdot.wa.gov/nw/002vc02158.jpg": "placeholder",
"https://images.wsdot.wa.gov/nw/005vc13921.jpg": "placeholder",
"https://images.wsdot.wa.gov/nw/005vc15591.jpg": "placeholder",
"https://images.wsdot.wa.gov/nw/005vc15607.jpg": "placeholder",
"https://images.wsdot.wa.gov/nw/005vc16195.jpg": "placeholder",
"https://images.wsdot.wa.gov/nw/005vc16237.jpg": "placeholder",
"https://images.wsdot.wa.gov/nw/005vc16396.jpg": "placeholder",
"https://images.wsdot.wa.gov/nw/005vc17281.jpg": "placeholder",
"https://images.wsdot.wa.gov/nw/005vc17287.jpg": "placeholder",
"https://images.wsdot.wa.gov/nw/005vc22518.jpg": "placeholder",
"https://images.wsdot.wa.gov/nw/005vc27623.jpg": "offline",
"https://images.wsdot.wa.gov/nw/018vc00198.jpg": "offline",
"https://images.wsdot.wa.gov/nw/020vc03293.jpg": "offline",
"https://images.wsdot.wa.gov/nw/090vc00973.jpg": "placeholder",
"https://images.wsdot.wa.gov/nw/090vc01581.jpg": "offline",
"https://images.wsdot.wa.gov/nw/099vc03098.jpg": "offline",
"https://images.wsdot.wa.gov/nw/104vc02886.jpg": "offline",
"https://images.wsdot.wa.gov/nw/167vc01165.jpg": "placeholder",
"https://images.wsdot.wa.gov/nw/167vc02501.jpg": "offline",
"https://images.wsdot.wa.gov/nw/405vc00537.jpg": "placeholder",
"https://images.wsdot.wa.gov/nw/405vc00602.jpg": "placeholder",
"https://images.wsdot.wa.gov/nw/405vc01762.jpg": "placeholder",
"https://images.wsdot.wa.gov/nw/405vc01808.jpg": "placeholder",
"https://images.wsdot.wa.gov/nw/405vc01820.jpg": "placeholder",
"https://images.wsdot.wa.gov/nw/405vc02093.jpg": "placeholder",
"https://images.wsdot.wa.gov/nw/405vc02103.jpg": "placeholder",
"https://images.wsdot.wa.gov/nw/509vc02956.jpg": "offline",
"https://images.wsdot.wa.gov/nw/516vc00198.jpg": "offline",
"https://images.wsdot.wa.gov/nw/516vc01267.jpg": "offline",
"https://images.wsdot.wa.gov/nw/520vc00400.jpg": "offline",
"https://images.wsdot.wa.gov/nw/532vc00337.jpg": "offline",
"https://images.wsdot.wa.gov/nw/539vc01510.jpg": "placeholder",
"https://images.wsdot.wa.gov/orflow/005vc09329.jpg": "placeholder",
"https://images.wsdot.wa.gov/orflow/005vc13341.jpg": "offline",
"https://images.wsdot.wa.gov/orflow/012vc00056.jpg": "placeholder",
"https://images.wsdot.wa.gov/orflow/099vc00018.jpg": "placeholder",
"https://images.wsdot.wa.gov/orflow/099vc00116.jpg": "offline",
"https://images.wsdot.wa.gov/orflow/101vc25064.jpg": "placeholder",
"https://images.wsdot.wa.gov/orflow/410vc01463.jpg": "placeholder",
"https://images.wsdot.wa.gov/orflow/410vc02141.jpg": "placeholder",
"https://images.wsdot.wa.gov/orflow/507vc03110.jpg": "placeholder",
"https://images.wsdot.wa.gov/orflow/512vc01143.jpg": "offline",
"https://images.wsdot.wa.gov/sw/005vc00044.jpg": "placeholder",
"https://images.wsdot.wa.gov/sw/005vc00426.jpg": "placeholder",
"https://images.wsdot.wa.gov/sw/005vc02311.jpg": "placeholder",
"https://images.wsdot.wa.gov/sw/005vc07330.jpg": "placeholder",
"https://images.wsdot.wa.gov/sw/007vc00124.jpg": "placeholder",
"https://images.wsdot.wa.gov/sw/012vc06922.jpg": "offline",
"https://images.wsdot.wa.gov/sw/432vc00986.jpg": "frozen",
"https://images.wsdot.wa.gov/wsf/Tahlequah/holding/holding.jpg": "placeholder",
"https://images.wsdot.wa.gov/wsf/colman/seattlemain.jpg": "placeholder",
"https://images.wsdot.wa.gov/wsf/vashon/VSHvc00001.jpg": "placeholder",
"https://images.wsdot.wa.gov/wsf/vashon/VSHvc00002.jpg": "placeholder",
"https://sunmountainlodge.com/wp-content/uploads/webcam/smlcam.jpg": "frozen"
}
}